stocktrim_public_api_client/__init__.py
stocktrim_public_api_client/client_types.py
stocktrim_public_api_client/stocktrim_client.py
stocktrim_public_api_client/utils.py
stocktrim_public_api_client/generated/__init__.py
stocktrim_public_api_client/generated/client.py
stocktrim_public_api_client/generated/errors.py
stocktrim_public_api_client/generated/api/__init__.py
stocktrim_public_api_client/generated/api/bill_of_materials/__init__.py
stocktrim_public_api_client/generated/api/bill_of_materials/delete_api_boms.py
stocktrim_public_api_client/generated/api/bill_of_materials/get_api_boms.py
stocktrim_public_api_client/generated/api/bill_of_materials/post_api_boms.py
stocktrim_public_api_client/generated/api/configuration/__init__.py
stocktrim_public_api_client/generated/api/configuration/get_api_configuration_configuration_name.py
stocktrim_public_api_client/generated/api/customers/__init__.py
stocktrim_public_api_client/generated/api/customers/get_api_customers.py
stocktrim_public_api_client/generated/api/customers/get_api_customers_code.py
stocktrim_public_api_client/generated/api/customers/put_api_customers.py
stocktrim_public_api_client/generated/api/in_flow/__init__.py
stocktrim_public_api_client/generated/api/in_flow/post_api_in_flow_tenant_id.py
stocktrim_public_api_client/generated/api/inventory/__init__.py
stocktrim_public_api_client/generated/api/inventory/post_api_inventory.py
stocktrim_public_api_client/generated/api/inventory_management_system_settings/__init__.py
stocktrim_public_api_client/generated/api/inventory_management_system_settings/get_api_inventory_management_system_settings.py
stocktrim_public_api_client/generated/api/inventory_management_system_settings/post_api_inventory_management_system_settings.py
stocktrim_public_api_client/generated/api/locations/__init__.py
stocktrim_public_api_client/generated/api/locations/get_api_locations.py
stocktrim_public_api_client/generated/api/locations/post_api_locations.py
stocktrim_openapi_client-0.11.0.dist-info/METADATA
stocktrim_openapi_client-0.11.0.dist-info/WHEEL
stocktrim_openapi_client-0.11.0.dist-info/entry_points.txt
stocktrim_openapi_client-0.11.0.dist-info/RECORD
